bytesight/__init__.py
bytesight/__main__.py
bytesight/events.py
bytesight/main.py
bytesight/profiler.py
bytesight/py.typed
bytesight-0.1.2.dist-info/METADATA
bytesight-0.1.2.dist-info/WHEEL
bytesight-0.1.2.dist-info/entry_points.txt
bytesight-0.1.2.dist-info/licenses/LICENSE
bytesight-0.1.2.dist-info/RECORD
