Metadata-Version: 2.4
Name: bytesight
Version: 0.1.2
Summary: A tracing profiler for Python bytecode
Author-email: Edmund Goodman <egoodman3141@gmail.com>
License: MIT License
License-File: LICENSE
Classifier: Development Status :: 2 - Pre-Alpha
Classifier: License :: OSI Approved :: MIT License
Classifier: Natural Language :: English
Classifier: Programming Language :: Python :: 3 :: Only
Classifier: Typing :: Typed
Requires-Python: >=3.10
